earthkit/meteo/__init__.py
earthkit/meteo/_version.py
earthkit/meteo/constants/__init__.py
earthkit/meteo/constants/constants.py
earthkit/meteo/extreme/__init__.py
earthkit/meteo/extreme/cpf.py
earthkit/meteo/extreme/efi.py
earthkit/meteo/extreme/sot.py
earthkit/meteo/extreme/array/__init__.py
earthkit/meteo/extreme/array/cpf.py
earthkit/meteo/extreme/array/efi.py
earthkit/meteo/extreme/array/sot.py
earthkit/meteo/score/__init__.py
earthkit/meteo/score/crps.py
earthkit/meteo/score/array/__init__.py
earthkit/meteo/score/array/crps.py
earthkit/meteo/solar/__init__.py
earthkit/meteo/solar/solar.py
earthkit/meteo/solar/array/__init__.py
earthkit/meteo/solar/array/solar.py
earthkit/meteo/stats/__init__.py
earthkit/meteo/stats/numpy_extended.py
earthkit/meteo/stats/quantiles.py
earthkit/meteo/stats/array/__init__.py
earthkit/meteo/stats/array/numpy_extended.py
earthkit/meteo/stats/array/quantiles.py
earthkit/meteo/thermo/__init__.py
earthkit/meteo/thermo/thermo.py
earthkit/meteo/thermo/array/__init__.py
earthkit/meteo/thermo/array/thermo.py
earthkit/meteo/vertical/__init__.py
earthkit/meteo/vertical/vertical.py
earthkit/meteo/vertical/array/__init__.py
earthkit/meteo/vertical/array/vertical.py
earthkit/meteo/wind/__init__.py
earthkit/meteo/wind/wind.py
earthkit/meteo/wind/array/__init__.py
earthkit/meteo/wind/array/wind.py
earthkit_meteo-0.4.0.dist-info/licenses/LICENSE
earthkit_meteo-0.4.0.dist-info/METADATA
earthkit_meteo-0.4.0.dist-info/WHEEL
earthkit_meteo-0.4.0.dist-info/top_level.txt
earthkit_meteo-0.4.0.dist-info/RECORD
