Metadata-Version: 2.4
Name: earthkit-meteo
Version: 0.4.0
Summary: Meteorological computations
Author-email: "European Centre for Medium-Range Weather Forecasts (ECMWF)" <software.support@ecmwf.int>
License: Apache License Version 2.0
Project-URL: Documentation, https://earthkit-meteo.readthedocs.io/
Project-URL: Homepage, https://github.com/ecmwf/earthkit-meteo/
Project-URL: Issues, https://github.com/ecmwf/earthkit-meteo.issues
Project-URL: Repository, https://github.com/ecmwf/earthkit-meteo/
Classifier: Development Status :: 2 - Pre-Alpha
Classifier: Intended Audience :: Developers
Classifier: License :: OSI Approved :: Apache Software License
Classifier: Operating System :: OS Independent
Classifier: Programming Language :: Python :: 3 :: Only
Classifier: Programming Language :: Python :: 3.8
Classifier: Programming Language :: Python :: 3.9
Classifier: Programming Language :: Python :: 3.10
Classifier: Programming Language :: Python :: 3.11
Classifier: Programming Language :: Python :: 3.12
Classifier: Programming Language :: Python :: Implementation :: CPython
Classifier: Programming Language :: Python :: Implementation :: PyPy
Requires-Python: >=3.8
License-File: LICENSE
Requires-Dist: numpy
Provides-Extra: test
Requires-Dist: pytest; extra == "test"
Requires-Dist: pytest-cov; extra == "test"
Dynamic: license-file
